{
  "plugins": [
    { "type": "cargo-workspace", "merge": false },
    { "type": "sentence-case" },
    {
      "type": "linked-versions",
      "groupName": "CCDB",
      "components": ["gluex-ccdb", "gluex-ccdb-py"]
    },
    {
      "type": "linked-versions",
      "groupName": "RCDB",
      "components": ["gluex-rcdb", "gluex-rcdb-py"]
    },
    {
      "type": "linked-versions",
      "groupName": "LUMI",
      "components": ["gluex-lumi", "gluex-lumi-py"]
    }
  ],
  "bump-minor-pre-major": true,
  "bump-patch-for-minor-pre-major": true,
  "release-type": "rust",
  "packages": {
    "crates/gluex-core": {
      "component": "gluex-core",
      "extra-files": [
        {
          "type": "toml",
          "path": "crates/gluex-ccdb/Cargo.toml",
          "jsonpath": "$.dependencies['gluex-core'].version"
        },
        {
          "type": "toml",
          "path": "crates/gluex-ccdb-py/Cargo.toml",
          "jsonpath": "$.dependencies['gluex-core'].version"
        },
        {
          "type": "toml",
          "path": "crates/gluex-rcdb/Cargo.toml",
          "jsonpath": "$.dependencies['gluex-core'].version"
        },
        {
          "type": "toml",
          "path": "crates/gluex-rcdb-py/Cargo.toml",
          "jsonpath": "$.dependencies['gluex-core'].version"
        },
        {
          "type": "toml",
          "path": "crates/gluex-lumi/Cargo.toml",
          "jsonpath": "$.dependencies['gluex-core'].version"
        },
        {
          "type": "toml",
          "path": "crates/gluex-lumi-py/Cargo.toml",
          "jsonpath": "$.dependencies['gluex-core'].version"
        }
      ]
    },
    "crates/gluex-ccdb": {
      "component": "gluex-ccdb",
      "extra-files": [
        {
          "type": "toml",
          "path": "crates/gluex-ccdb-py/Cargo.toml",
          "jsonpath": "$.dependencies['gluex-ccdb'].version"
        },
        {
          "type": "toml",
          "path": "crates/gluex-lumi/Cargo.toml",
          "jsonpath": "$.dependencies['gluex-ccdb'].version"
        }
      ]
    },
    "crates/gluex-ccdb-py": {
      "component": "gluex-ccdb-py"
    },
    "crates/gluex-rcdb": {
      "component": "gluex-rcdb",
      "extra-files": [
        {
          "type": "toml",
          "path": "crates/gluex-rcdb-py/Cargo.toml",
          "jsonpath": "$.dependencies['gluex-rcdb'].version"
        },
        {
          "type": "toml",
          "path": "crates/gluex-lumi/Cargo.toml",
          "jsonpath": "$.dependencies['gluex-rcdb'].version"
        }
      ]
    },
    "crates/gluex-rcdb-py": {
      "component": "gluex-rcdb-py"
    },
    "crates/gluex-lumi": {
      "component": "gluex-lumi",
      "extra-files": [
        {
          "type": "toml",
          "path": "crates/gluex-lumi-py/Cargo.toml",
          "jsonpath": "$.dependencies['gluex-lumi'].version"
        }
      ]
    },
    "crates/gluex-lumi-py": {
      "component": "gluex-lumi-py"
    }
  }
}
